Single_port_RAM/Single_port_ram.v
module single_port_ram #(
    parameter ADDR_WIDTH = 4, //4 bit address
    parameter DATA_WIDTH = 32, //32 bits data stream
    parameter DEPTH = 16 //16 registers available in RAM
) 
(
    input                  clk, //clock of the module
    input [ADDR_WIDTH-1:0] addr,//4 bits memory address
    inout [DATA_WIDTH-1:0] data,//32 bits data can be written
    input                  cs,  //control signal from the chip select port
    input                  we,  // write enable port for convert RAM to written in memory mode
    input                  oe   // Output enable port for convert RAM to reading mode from RAM
);

reg [DATA_WIDTH-1:0]  temp_data; 
reg [DATA_WIDTH-1:0]  mem[DEPTH];

always @(posedge clk) begin
    if (cs & we) begin
       mem[addr] <= data;     // write the data to the memory location specified by address   
    end
end

always @(posedge clk) begin
    if (cs & !we)
     temp_data <= mem[addr]; //read the data from the memory location specified by address
end
    

assign data = cs & oe & !we ? temp_data : 'hz; //If the chip select cs is active, output enable oe is active, and write enable we is inactive, it assigns the value of temp_data to data. Otherwise, it assigns high-impedance ('hz) to data, indicating that the output should be in a high-impedance state.

    
endmodule

Single_port_RAM/Single_port_ram_tb.v
`timescale 1ns/1ns
`include "Single_port_ram.v"


module single_port_ram_tb;
 
 parameter ADDR_WIDTH = 4;
 parameter DATA_WIDTH = 16;
 parameter DEPTH = 16;

 reg clk;
 reg cs;
 reg we;
 reg oe;
 reg [ADDR_WIDTH-1:0] addr;
 wire [DATA_WIDTH-1:0] data;
 reg [DATA_WIDTH-1:0] tb_data;

 single_port_ram #(.DATA_WIDTH(DATA_WIDTH)) u0
 (                        .clk(clk),
                          .addr(addr),
                          .data(data),
                          .cs(cs),
                          .we(we),
                          .oe(oe));
 

 always #10 clk = ~clk;
 assign data = !oe ? tb_data : 'hz; //when oe inactive assign tb_data to data

 initial begin
 
    $dumpfile("Single_port_ram_tb.vcd");
    $dumpvars(0,single_port_ram_tb);

 {clk, cs, we, addr, tb_data, oe} <= 0;

 repeat (2) @ (posedge clk); //wait for two positive edges to ensure proper initialization

 for (integer i =0; i<2**ADDR_WIDTH; i=i+1) begin //check RAM for each address value by writing random values (write operation)
    repeat (1) @(posedge clk); 
    addr <= i; 
    we <= 1; 
    cs <= 1; 
    oe <= 0; 
    tb_data <= $random;
 end
 
 for (integer i = 0;i < 2**ADDR_WIDTH ; i=i+1 ) begin //check read operation
    repeat (1) @(posedge clk);
    addr <= i; 
    we <= 0; 
    cs <= 1; 
    oe <= 1;
 end
  
  #20 
  $display("Test Complete");
  $finish;
 end

  initial
    $monitor ("cs=%b, we=%b, oe=%b, tb_data=%b, addr=%b, data=%b",cs,we,oe,tb_data,addr,data);

endmodule

Single_port_RAM/Single_port_ram_tb.vcd
$date
	Fri Jul 07 22:29:48 2023
$end
$version
	Icarus Verilog
$end
$timescale
	1ns
$end
$scope module single_port_ram_tb $end
$var wire 16 ! data [15:0] $end
$var parameter 32 " ADDR_WIDTH $end
$var parameter 32 # DATA_WIDTH $end
$var parameter 32 $ DEPTH $end
$var reg 4 % addr [3:0] $end
$var reg 1 & clk $end
$var reg 1 ' cs $end
$var reg 1 ( oe $end
$var reg 16 ) tb_data [15:0] $end
$var reg 1 * we $end
$scope module u0 $end
$var wire 4 + addr [3:0] $end
$var wire 1 & clk $end
$var wire 1 ' cs $end
$var wire 16 , data [15:0] $end
$var wire 1 ( oe $end
$var wire 1 * we $end
$var parameter 32 - ADDR_WIDTH $end
$var parameter 32 . DATA_WIDTH $end
$var parameter 32 / DEPTH $end
$var reg 16 0 temp_data [15:0] $end
$upscope $end
$scope begin $ivl_for_loop0 $end
$var integer 32 1 i [31:0] $end
$upscope $end
$scope begin $ivl_for_loop1 $end
$var integer 32 2 i [31:0] $end
$upscope $end
$upscope $end
$enddefinitions $end
$comment Show the parameter values. $end
$dumpall
b10000 /
b10000 .
b100 -
b10000 $
b10000 #
b100 "
$end
#0
$dumpvars
bx 2
bx 1
bx 0
b0 ,
b0 +
0*
b0 )
0(
0'
0&
b0 %
b0 !
$end
#10
1&
#20
0&
#30
b0 1
1&
#40
0&
#50
b11010100100100 !
b11010100100100 ,
b11010100100100 )
1'
1*
b1 1
1&
#60
0&
#70
b101111010000001 !
b101111010000001 ,
b101111010000001 )
b1 %
b1 +
b10 1
1&
#80
0&
#90
b1101011000001001 !
b1101011000001001 ,
b1101011000001001 )
b10 %
b10 +
b11 1
1&
#100
0&
#110
b101011001100011 !
b101011001100011 ,
b101011001100011 )
b11 %
b11 +
b100 1
1&
#120
0&
#130
b111101100001101 !
b111101100001101 ,
b111101100001101 )
b100 %
b100 +
b101 1
1&
#140
0&
#150
b1001100110001101 !
b1001100110001101 ,
b1001100110001101 )
b101 %
b101 +
b110 1
1&
#160
0&
#170
b1000010001100101 !
b1000010001100101 ,
b1000010001100101 )
b110 %
b110 +
b111 1
1&
#180
0&
#190
b101001000010010 !
b101001000010010 ,
b101001000010010 )
b111 %
b111 +
b1000 1
1&
#200
0&
#210
b1110001100000001 !
b1110001100000001 ,
b1110001100000001 )
b1000 %
b1000 +
b1001 1
1&
#220
0&
#230
b1100110100001101 !
b1100110100001101 ,
b1100110100001101 )
b1001 %
b1001 +
b1010 1
1&
#240
0&
#250
b1111000101110110 !
b1111000101110110 ,
b1111000101110110 )
b1010 %
b1010 +
b1011 1
1&
#260
0&
#270
b1100110100111101 !
b1100110100111101 ,
b1100110100111101 )
b1011 %
b1011 +
b1100 1
1&
#280
0&
#290
b101011111101101 !
b101011111101101 ,
b101011111101101 )
b1100 %
b1100 +
b1101 1
1&
#300
0&
#310
b1111011110001100 !
b1111011110001100 ,
b1111011110001100 )
b1101 %
b1101 +
b1110 1
1&
#320
0&
#330
b1110100111111001 !
b1110100111111001 ,
b1110100111111001 )
b1110 %
b1110 +
b1111 1
1&
#340
0&
#350
b10010011000110 !
b10010011000110 ,
b10010011000110 )
b1111 %
b1111 +
b0 2
b10000 1
1&
#360
0&
#370
bx !
bx ,
1(
0*
b0 %
b0 +
b1 2
1&
#380
0&
#390
b11010100100100 !
b11010100100100 ,
b1 %
b1 +
b11010100100100 0
b10 2
1&
#400
0&
#410
b101111010000001 !
b101111010000001 ,
b101111010000001 0
b10 %
b10 +
b11 2
1&
#420
0&
#430
b1101011000001001 !
b1101011000001001 ,
b11 %
b11 +
b1101011000001001 0
b100 2
1&
#440
0&
#450
b101011001100011 !
b101011001100011 ,
b101011001100011 0
b100 %
b100 +
b101 2
1&
#460
0&
#470
b111101100001101 !
b111101100001101 ,
b101 %
b101 +
b111101100001101 0
b110 2
1&
#480
0&
#490
b1001100110001101 !
b1001100110001101 ,
b1001100110001101 0
b110 %
b110 +
b111 2
1&
#500
0&
#510
b1000010001100101 !
b1000010001100101 ,
b111 %
b111 +
b1000010001100101 0
b1000 2
1&
#520
0&
#530
b101001000010010 !
b101001000010010 ,
b101001000010010 0
b1000 %
b1000 +
b1001 2
1&
#540
0&
#550
b1110001100000001 !
b1110001100000001 ,
b1001 %
b1001 +
b1110001100000001 0
b1010 2
1&
#560
0&
#570
b1100110100001101 !
b1100110100001101 ,
b1100110100001101 0
b1010 %
b1010 +
b1011 2
1&
#580
0&
#590
b1111000101110110 !
b1111000101110110 ,
b1011 %
b1011 +
b1111000101110110 0
b1100 2
1&
#600
0&
#610
b1100110100111101 !
b1100110100111101 ,
b1100110100111101 0
b1100 %
b1100 +
b1101 2
1&
#620
0&
#630
b101011111101101 !
b101011111101101 ,
b1101 %
b1101 +
b101011111101101 0
b1110 2
1&
#640
0&
#650
b1111011110001100 !
b1111011110001100 ,
b1111011110001100 0
b1110 %
b1110 +
b1111 2
1&
#660
0&
#670
b1110100111111001 !
b1110100111111001 ,
b1111 %
b1111 +
b1110100111111001 0
b10000 2
1&
#680
0&
#690
b10010011000110 !
b10010011000110 ,
b10010011000110 0
1&
