ALU/alu.v
// From the book: "But How Do It Know?" pg. 87, 88
// Written by: J. Clark Scott
//
//
// Verilog HDL implementation of the computer described in the book.
// Created and all credits goes to: David J. Marion
//
// Arithmetic and Logic Unit (ALU)
`timescale 1ns / 1ps
module alu(
	input [7:0] A,			// input operand 1
	input [7:0] B,			// input operand 2
	input c_in,				// carry in signal
	input [2:0] op,			// 3-bit opcode = maximum 8 instructions
	output [7:0] C,			// output result 
	output c_out,			// carry out signal
	output a_larger,		// A > B signal
	output equal,			// A == B signal
	output zero				// ALU result = 0 signal
	);
	
	// All 8 opcodes symbolically defined by octo notation
	parameter [2:0] ADD = 3'o0, // Addition
					RSH = 3'o1,	// right shift
					LSH = 3'o2,	// left shift
					NOT = 3'o3, // NOT operation
					AND = 3'o4, // AND operation
					OR  = 3'o5, // OR operation
					XOR = 3'o6, // XOR operation
					CMP = 3'o7; // Compare operation
	
	reg [8:0] out_reg;		// We need a ninth bit for the carry out from addition
	
	always @*
		case(op)
			ADD : out_reg <= A + B + c_in;
			RSH : out_reg <= {c_in, A[7:1]};
			LSH : out_reg <= {A[6:0], c_in};
			NOT : out_reg <= ~A;
			AND : out_reg <= A & B;
			OR  : out_reg <= A | B;
			XOR : out_reg <= A ^ B;
			CMP : out_reg <= A ^ B;			// Compare, used to set flags
		endcase
			   
	assign C = out_reg[7:0];	// ALU result
	assign zero = ~|C;			// reduction NOR to determine if result = 0
	assign equal = ((op == CMP) && (zero == 1'b1)) ? 1'b1 : 1'b0;	// At the compare operation, zero flag remain one, then equal port is one otherwise zero
	assign a_larger = ((op == CMP) && (A > B)) ? 1'b1 : 1'b0;  // At the compare operation, A larger than the B, then a_larger poer become one
	assign c_out = (op == ADD) ? out_reg[8]: (op == RSH) ? A[0]: (op == LSH) ? A[7]: 1'b0; //At the Addition, 9th bit of output register and At the Right shift, 1st bit of A and At the Left shift, 8th bit will be c out
	
endmodule

ALU/alu_tb.v
// From the book: "But How Do It Know?" pg. 87, 88
// Written by: J. Clark Scott
// TESTBENCH for Arithmetic and Logic Unit (ALU)
`timescale 1ns / 1ps
`include "alu.v"

module alu_TB;
	reg [7:0] A, B;
	reg c_in;
	reg [2:0] op;
	wire [7:0] C;
	wire c_out, a_larger, equal, zero;

	// ALU Operation Codes
	parameter [2:0] ADD = 3'o0,
					RSH = 3'o1,
					LSH = 3'o2,
					NOT = 3'o3,
					AND = 3'o4,
					OR  = 3'o5,
					XOR = 3'o6,
					CMP = 3'o7;

	// Instantiate the device under test (DUT) and connect test bench signals to DUT I/O
	alu DUT(
		.A(A),
		.B(B),
		.c_in(c_in),
		.op(op),
		.C(C),
		.c_out(c_out),
		.a_larger(a_larger),
		.equal(equal),
		.zero(zero)
	);

	initial begin
		$dumpfile("alu.vcd");	// specify the name of the file for GTKWave
		$dumpvars(0, alu_TB);	// specify the level of variables to dump to above file (0 = all)
	end
	
	initial begin
		// Initialize register values
		c_in = 0;
		A = 8'haa;		// <- 8'b1010_1010
		B = 8'h55;		// <- 8'b0101_0101
		
        //check the addition
		op = ADD;		// -> 8'b1111_1111
		#1 c_in = 1;	// -> 8'b0000_0000, flags set -> zero, c_out
		#1 c_in = 0;
		#1;
		
        //check the Right hand shift
		A = 8'h0c;		// <- 8'b0000_1100
		op = RSH;		// -> 8'b0000_0110
		#1 c_in = 1;	// -> 8'b1000_0110
		#1 c_in = 0;	// -> 8'b0000_0110
		#1;
		
        //check the left hand shift
		A = 8'h16;		// <- 8'b0001_0110
		op = LSH;		// -> 8'b0010_1100
		#1 c_in = 1;	// -> 8'b0010_1101
		#1 c_in = 0;	// -> 8'b0010_1100
		#1;
		
        //check the c out when right hand shift operate
		A = 8'h81;		// <- 8'b1000_0001
		op = RSH;		// -> 8'b0100_0000, flags set -> c_out
		#1;
		
        //check the c out when left hand shift operate
		A = 8'h81;		// -> 8'b1000_0001
		op = LSH;		// -> 8'b0000_0010, flags set -> c_out
		#1;
		
        //check the NOT operation
		A = 8'haa;		// <- 8'b1010_1010
		op = NOT;		// -> 8'b0101_0101
		#1;
		
        //check the AND operation
		B = 8'h55;		// <- 8'b0101_0101
		op = AND;		// -> 8'b0000_0000, flags set -> zero
		#1;
		
        //check OR operation
		op = OR;		// -> 8'b1111_1111
		#1;
		
        //check XOR operation
		op = XOR;		// -> 8'b1111_1111
		#1;
		
        //check compare operation for equal
		B = 8'haa;		// <- 8'b1010_1010
		op = CMP;		// -> 8'b0000_0000, flags set -> equal, zero
		#1;
		
        //check compare operation for A larger situation
		A = 8'hac;		// <- 8'b1010_1100
		op = CMP;		// -> 8'b0000_0110, flags set -> a_larger
		#1;
		
        $display("Test Complete");
		$finish;	
	end

initial
    $monitor ("A=%b,B=%b,carry in=%b,opcode=%b,C=%b,carry out=%b,A larger=%b, Equal=%b,zero=%b",A,B,c_in,op,C,c_out,a_larger,equal,zero);

endmodule

ALU/alu.vcd
$date
	Sat Jul 08 17:45:06 2023
$end
$version
	Icarus Verilog
$end
$timescale
	1ps
$end
$scope module alu_TB $end
$var wire 1 ! zero $end
$var wire 1 " equal $end
$var wire 1 # c_out $end
$var wire 1 $ a_larger $end
$var wire 8 % C [7:0] $end
$var parameter 3 & ADD $end
$var parameter 3 ' AND $end
$var parameter 3 ( CMP $end
$var parameter 3 ) LSH $end
$var parameter 3 * NOT $end
$var parameter 3 + OR $end
$var parameter 3 , RSH $end
$var parameter 3 - XOR $end
$var reg 8 . A [7:0] $end
$var reg 8 / B [7:0] $end
$var reg 1 0 c_in $end
$var reg 3 1 op [2:0] $end
$scope module DUT $end
$var wire 8 2 A [7:0] $end
$var wire 8 3 B [7:0] $end
$var wire 1 0 c_in $end
$var wire 3 4 op [2:0] $end
$var wire 1 ! zero $end
$var wire 1 " equal $end
$var wire 1 # c_out $end
$var wire 1 $ a_larger $end
$var wire 8 5 C [7:0] $end
$var parameter 3 6 ADD $end
$var parameter 3 7 AND $end
$var parameter 3 8 CMP $end
$var parameter 3 9 LSH $end
$var parameter 3 : NOT $end
$var parameter 3 ; OR $end
$var parameter 3 < RSH $end
$var parameter 3 = XOR $end
$var reg 9 > out_reg [8:0] $end
$upscope $end
$upscope $end
$enddefinitions $end
$comment Show the parameter values. $end
$dumpall
b110 =
b1 <
b101 ;
b11 :
b10 9
b111 8
b100 7
b0 6
b110 -
b1 ,
b101 +
b11 *
b10 )
b111 (
b100 '
b0 &
$end
#0
$dumpvars
b11111111 >
b11111111 5
b0 4
b1010101 3
b10101010 2
b0 1
00
b1010101 /
b10101010 .
b11111111 %
0$
0#
0"
0!
$end
#1000
1#
1!
b0 %
b0 5
b100000000 >
10
#2000
0#
0!
b11111111 %
b11111111 5
b11111111 >
00
#3000
b110 %
b110 5
b110 >
b1 1
b1 4
b1100 .
b1100 2
#4000
b10000110 %
b10000110 5
b10000110 >
10
#5000
b110 %
b110 5
b110 >
00
#6000
b101100 %
b101100 5
b101100 >
b10 1
b10 4
b10110 .
b10110 2
#7000
b101101 %
b101101 5
b101101 >
10
#8000
b101100 %
b101100 5
b101100 >
00
#9000
b1000000 %
b1000000 5
b1000000 >
1#
b1 1
b1 4
b10000001 .
b10000001 2
#10000
b10 %
b10 5
b10 >
b10 1
b10 4
#11000
b1010101 %
b1010101 5
b101010101 >
0#
b11 1
b11 4
b10101010 .
b10101010 2
#12000
1!
b0 %
b0 5
b0 >
b100 1
b100 4
#13000
0!
b11111111 %
b11111111 5
b11111111 >
b101 1
b101 4
#14000
b110 1
b110 4
#15000
1"
1!
b0 %
b0 5
b0 >
b111 1
b111 4
b10101010 /
b10101010 3
#16000
0"
0!
b110 %
b110 5
b110 >
1$
b10101100 .
b10101100 2
