Clock_Stepper/clock_gen.v
// From the book: "But How Do It Know?" pg. 96, 97
// Written by: J. Clark Scott
//
// Verilog HDL implementation of the computer described in the book.
// Created and all credits goes to: David J. Marion
//
// Clock Module
`timescale 1ns / 1ps
module clock_gen(
	input sys_clk,		// system input clock of arbitrary frequency
	output clk,			// stepper clock
	output clk_e,		// enable clock
	output clk_s		// set clock
	);
	
	reg [1:0] clk_reg = 2'b00; //clock register start from 0
	
	always @(posedge sys_clk)
		clk_reg <= clk_reg + 1; //increment of the clock register 1,2
		
	assign clk = ((clk_reg == 2'b00) || (clk_reg == 2'b01)) ? 1'b1 : 1'b0; //If clock reg 0 or 1, then clk become 1
	assign clk_e = clk_reg == 2'b11 ? 1'b0 : 1'b1; //If clock reg 3 then enable clock become 1
	assign clk_s = clk_reg == 2'b01 ? 1'b1 : 1'b0; //If clock reg 1 them set clock become 1
	
endmodule

Clock_Stepper/clock_gen_tb.v
// From the book: "But How Do It Know?" pg. 96, 97
// Written by: J. Clark Scott
//
// Verilog HDL implementation of the computer described in the book.
// Created and all credits goes to: David J. Marion
//
// TEST BENCH for Clock Module
`timescale 1ns / 1ps
`include "clock_gen.v"
module clock_gen_TB;
	
	reg sys_clk;
	wire clk, clk_e, clk_s;
	
	clock_gen DUT(
		.sys_clk(sys_clk),
		.clk(clk),
		.clk_e(clk_e),
		.clk_s(clk_s)
	);
	
	always #1 sys_clk = ~sys_clk;
	
	initial begin
		$dumpfile("clk_gen.vcd");
		$dumpvars(0, clock_gen_TB);
	end
	
	initial begin
		sys_clk = 1'b0;	// Initialize system clock
        #40 
        $display("Test Complete");
		$finish;
	end
	
endmodule

Clock_Stepper/clk_gen.vcd
$date
	Sat Jul 08 21:28:21 2023
$end
$version
	Icarus Verilog
$end
$timescale
	1ps
$end
$scope module clock_gen_TB $end
$var wire 1 ! clk_s $end
$var wire 1 " clk_e $end
$var wire 1 # clk $end
$var reg 1 $ sys_clk $end
$scope module DUT $end
$var wire 1 $ sys_clk $end
$var wire 1 ! clk_s $end
$var wire 1 " clk_e $end
$var wire 1 # clk $end
$var reg 2 % clk_reg [1:0] $end
$upscope $end
$upscope $end
$enddefinitions $end
$comment Show the parameter values. $end
$dumpall
$end
#0
$dumpvars
b0 %
0$
1#
1"
0!
$end
#1000
1!
b1 %
1$
#2000
0$
#3000
0#
0!
b10 %
1$
#4000
0$
#5000
0"
b11 %
1$
#6000
0$
#7000
1#
1"
b0 %
1$
#8000
0$
#9000
1!
b1 %
1$
#10000
0$
#11000
0#
0!
b10 %
1$
#12000
0$
#13000
0"
b11 %
1$
#14000
0$
#15000
1#
1"
b0 %
1$
#16000
0$
#17000
1!
b1 %
1$
#18000
0$
#19000
0#
0!
b10 %
1$
#20000
0$
#21000
0"
b11 %
1$
#22000
0$
#23000
1#
1"
b0 %
1$
#24000
0$
#25000
1!
b1 %
1$
#26000
0$
#27000
0#
0!
b10 %
1$
#28000
0$
#29000
0"
b11 %
1$
#30000
0$
#31000
1#
1"
b0 %
1$
#32000
0$
#33000
1!
b1 %
1$
#34000
0$
#35000
0#
0!
b10 %
1$
#36000
0$
#37000
0"
b11 %
1$
#38000
0$
#39000
1#
1"
b0 %
1$
