Control_unit/stepper.v
// From the book: "But How Do It Know?" pg. 102
// Written by: J. Clark Scott
// Verilog HDL implementation of the computer described in the book.
// Created and all credits goes to: David J. Marion
//
// Stepper Module
// A 7th step is not needed.
`timescale 1ns / 1ps
module stepper(
	input clk,								// stepper clock
	input reset,							// system reset
	output reg [5:0] step = 6'b10_0000		// begin at step 1
	);
	
	always @(posedge clk or posedge reset) begin
		if (reset)
			step <= 6'b10_0000;				// system reset back to step 1
		else
			if (step == 6'b00_0001)			// when we get to last step
				step <= 6'b10_0000;			// go back to the first step
			else
				step <= step >> 1;			// otherwise, shift right by 1 to next step
	end
endmodule

Clock_Stepper/stepper_tb.v
// From the book: "But How Do It Know?" pg. 102
// Written by: J. Clark Scott
//
// Verilog HDL implementation of the computer described in the book.
// Created and all credits goes to: David J. Marion
//
// TEST BENCH for Stepper Module
`timescale 1ns / 1ps
`include "stepper.v"
module stepper_TB;
	
	reg clk;
	wire [5:0] step;
	
	stepper STEPPER(
		.clk(clk),
		.step(step)
	);

	always #1 clk = ~clk;
	
	initial begin
		$dumpfile("stepper.vcd");
		$dumpvars(0, stepper_TB);
	end
	
	initial begin
		clk = 0;	// Initialize clock 
		#50
        $display("Test Complete");
        $finish;
	end


endmodule

Clock_Stepper/stepper.vcd
$date
	Sat Jul 08 21:48:11 2023
$end
$version
	Icarus Verilog
$end
$timescale
	1ps
$end
$scope module stepper_TB $end
$var wire 6 ! step [5:0] $end
$var reg 1 " clk $end
$scope module STEPPER $end
$var wire 1 " clk $end
$var wire 1 # reset $end
$var reg 6 $ step [5:0] $end
$upscope $end
$upscope $end
$enddefinitions $end
$comment Show the parameter values. $end
$dumpall
$end
#0
$dumpvars
b100000 $
z#
0"
b100000 !
$end
#1000
b10000 !
b10000 $
1"
#2000
0"
#3000
b1000 !
b1000 $
1"
#4000
0"
#5000
b100 !
b100 $
1"
#6000
0"
#7000
b10 !
b10 $
1"
#8000
0"
#9000
b1 !
b1 $
1"
#10000
0"
#11000
b100000 !
b100000 $
1"
#12000
0"
#13000
b10000 !
b10000 $
1"
#14000
0"
#15000
b1000 !
b1000 $
1"
#16000
0"
#17000
b100 !
b100 $
1"
#18000
0"
#19000
b10 !
b10 $
1"
#20000
0"
#21000
b1 !
b1 $
1"
#22000
0"
#23000
b100000 !
b100000 $
1"
#24000
0"
#25000
b10000 !
b10000 $
1"
#26000
0"
#27000
b1000 !
b1000 $
1"
#28000
0"
#29000
b100 !
b100 $
1"
#30000
0"
#31000
b10 !
b10 $
1"
#32000
0"
#33000
b1 !
b1 $
1"
#34000
0"
#35000
b100000 !
b100000 $
1"
#36000
0"
#37000
b10000 !
b10000 $
1"
#38000
0"
#39000
b1000 !
b1000 $
1"
#40000
0"
#41000
b100 !
b100 $
1"
#42000
0"
#43000
b10 !
b10 $
1"
#44000
0"
#45000
b1 !
b1 $
1"
#46000
0"
#47000
b100000 !
b100000 $
1"
#48000
0"
#49000
b10000 !
b10000 $
1"
